ansaotuvi/AmDuong.py
ansaotuvi/App.py
ansaotuvi/DiaBan.py
ansaotuvi/Lich_EPHEM.py
ansaotuvi/Lich_HND.py
ansaotuvi/Sao.py
ansaotuvi/ThienBan.py
ansaotuvi/__init__.py
ansaotuvi-0.1.28.dist-info/LICENSE
ansaotuvi-0.1.28.dist-info/METADATA
ansaotuvi-0.1.28.dist-info/WHEEL
ansaotuvi-0.1.28.dist-info/top_level.txt
ansaotuvi-0.1.28.dist-info/RECORD
