Metadata-Version: 2.1
Name: ansaotuvi
Version: 0.1.28
Summary: New package for ansaotuvi
Home-page: https://github.com/hieudo-ursa/ansaotuvi
Author: hieu.do
Author-email: "hieu.do" <hieu.do@ursa.vn>
License: MIT License
Project-URL: Homepage, https://github.com/hieudo-ursa/ansaotuvi
Project-URL: Issues, https://github.com/hieudo-ursa/ansaotuvi/issues
Classifier: Programming Language :: Python :: 3
Classifier: License :: OSI Approved :: MIT License
Classifier: Operating System :: OS Independent
Requires-Python: >=3.8
License-File: LICENSE
